Metadata-Version: 2.1
Name: jcast
Version: 0.3.5
Summary: JCAST uses splice junction information from RNA-seq data to create custom protein databases
Home-page: https://github.com/ed-lau/jcast
Author: Edward Lau, Maggie Lam
Author-email: edward.lau@cuanschutz.edu
License: UNKNOWN
Project-URL: Source, https://github.com/ed-lau/jcast
Project-URL: Lau Lab Colorado, https://www.laulab.net
Keywords: scientific multi-omics isoform mass-spectrometry
Platform: UNKNOWN
Classifier: Development Status :: 4 - Beta
Classifier: Intended Audience :: Developers
Classifier: Topic :: Software Development :: Build Tools
Classifier: License :: OSI Approved :: MIT License
Classifier: Programming Language :: Python :: 3.6
Classifier: Programming Language :: Python :: 3.7
Classifier: Programming Language :: Python :: 3.8
Classifier: Programming Language :: Python :: 3.9
Classifier: Programming Language :: Python :: 3 :: Only
Requires-Python: >=3.7, <4
License-File: LICENSE.md
